wechaty_puppet_service/__init__.py
wechaty_puppet_service/config.py
wechaty_puppet_service/puppet.py
wechaty_puppet_service/py.typed
wechaty_puppet_service/utils.py
wechaty_puppet_service/version.py
wechaty_puppet_service/version_test.py
wechaty_puppet_service-0.8.10.dist-info/LICENSE
wechaty_puppet_service-0.8.10.dist-info/METADATA
wechaty_puppet_service-0.8.10.dist-info/WHEEL
wechaty_puppet_service-0.8.10.dist-info/top_level.txt
wechaty_puppet_service-0.8.10.dist-info/RECORD
