Metadata-Version: 2.1
Name: wechaty-puppet-service
Version: 0.8.10
Summary: Python Service Puppet for Wechaty
Home-page: https://github.com/wechaty/python-wechaty-puppet-service
Author: Huan LI (李卓桓)
Author-email: zixia@zixia.net
License: Apache-2.0
Platform: UNKNOWN
Classifier: Programming Language :: Python :: 3.7
Classifier: License :: OSI Approved :: Apache Software License
Classifier: Operating System :: OS Independent
Requires-Dist: pyee
Requires-Dist: requests
Requires-Dist: wechaty-grpc (~=0.20.19)
Requires-Dist: ping3
